xkits_file/__init__.py
xkits_file/attribute.py
xkits_file/download.py
xkits_file/filestat.py
xkits_file/linefile.py
xkits_file/safefile.py
xkits_file/scanner.py
xkits_fileviewer/__init__.py
xkits_fileviewer/linefile.py
xkits_file-0.7.dist-info/LICENSE
xkits_file-0.7.dist-info/METADATA
xkits_file-0.7.dist-info/WHEEL
xkits_file-0.7.dist-info/entry_points.txt
xkits_file-0.7.dist-info/top_level.txt
xkits_file-0.7.dist-info/zip-safe
xkits_file-0.7.dist-info/RECORD
