Metadata-Version: 2.1
Name: xkits-file
Version: 0.7
Summary: File module
Home-page: https://github.com/bondbox/xfiles/
Author: Mingzhe Zou
Author-email: zoumingzhe@outlook.com
License: GPLv2
Project-URL: Source Code, https://github.com/bondbox/xfiles/
Project-URL: Bug Tracker, https://github.com/bondbox/xfiles/issues
Project-URL: Documentation, https://github.com/bondbox/xfiles/
Keywords: file
Platform: any
Classifier: Programming Language :: Python
Classifier: Programming Language :: Python :: 3
Requires-Python: >=3.8
License-File: LICENSE
Requires-Dist: xkits-command >=0.5.0
Requires-Dist: xkits-lib >=0.4
Requires-Dist: filelock
